{
  "voters": [
    {
      "VIN": "507",
      "firstName": "fg",
      "lastName": "fggf",
      "otherName": "df",
      "phone": "34",
      "email": "sd@g",
      "state": "tr",
      "id": 1
    },
    {
      "VIN": "226",
      "firstName": "dssdd",
      "lastName": "dssdd",
      "otherName": "dsds",
      "phone": "32",
      "email": "sd@f",
      "state": "df",
      "id": 2
    },
    {
      "id": 3
    },
    {
      "id": 4
    }
  ],
  "candidates": [
    {
      "candidateId": "136",
      "firstName": "don",
      "lastName": "john",
      "office": "president",
      "email": "donjoe@gmail.com",
      "politicalParty": "PPR",
      "description": "",
      "id": 1
    },
    {
      "candidateId": "190",
      "firstName": "don",
      "lastName": "dan",
      "office": "president",
      "email": "donjoe@gmail.com",
      "politicalParty": "PPR",
      "description": "f",
      "id": 2
    }
  ]
}